odoo/addons/sale_coupon_criteria_order_based/README.rst
odoo/addons/sale_coupon_criteria_order_based/__init__.py
odoo/addons/sale_coupon_criteria_order_based/__manifest__.py
odoo/addons/sale_coupon_criteria_order_based/i18n/es.po
odoo/addons/sale_coupon_criteria_order_based/i18n/it.po
odoo/addons/sale_coupon_criteria_order_based/i18n/sale_coupon_criteria_order_based.pot
odoo/addons/sale_coupon_criteria_order_based/models/__init__.py
odoo/addons/sale_coupon_criteria_order_based/models/coupon_coupon.py
odoo/addons/sale_coupon_criteria_order_based/models/coupon_program.py
odoo/addons/sale_coupon_criteria_order_based/models/coupon_rule.py
odoo/addons/sale_coupon_criteria_order_based/readme/CONTRIBUTORS.rst
odoo/addons/sale_coupon_criteria_order_based/readme/DESCRIPTION.rst
odoo/addons/sale_coupon_criteria_order_based/readme/USAGE.rst
odoo/addons/sale_coupon_criteria_order_based/static/description/icon.png
odoo/addons/sale_coupon_criteria_order_based/static/description/index.html
odoo/addons/sale_coupon_criteria_order_based/tests/__init__.py
odoo/addons/sale_coupon_criteria_order_based/tests/test_sale_coupon_criteria_order_based.py
odoo/addons/sale_coupon_criteria_order_based/views/coupon_program_view.xml
odoo_addon_sale_coupon_criteria_order_based-15.0.1.0.1.dist-info/METADATA
odoo_addon_sale_coupon_criteria_order_based-15.0.1.0.1.dist-info/WHEEL
odoo_addon_sale_coupon_criteria_order_based-15.0.1.0.1.dist-info/top_level.txt
odoo_addon_sale_coupon_criteria_order_based-15.0.1.0.1.dist-info/RECORD
